face_detection/__init__.py
face_detection/face_dt.py
face_detec-0.0.6.dist-info/METADATA
face_detec-0.0.6.dist-info/WHEEL
face_detec-0.0.6.dist-info/top_level.txt
face_detec-0.0.6.dist-info/RECORD
